devops_mcps/__init__.py
devops_mcps/artifactory.py
devops_mcps/azure.py
devops_mcps/cache.py
devops_mcps/core.py
devops_mcps/github.py
devops_mcps/inputs.py
devops_mcps/jenkins.py
devops_mcps/logger.py
devops_mcps/main_entry.py
devops_mcps/mcp_tools.py
devops_mcps/prompt_management.py
devops_mcps/prompts.py
devops_mcps/server_setup.py
devops_mcps/utils/__init__.py
devops_mcps/utils/artifactory/__init__.py
devops_mcps/utils/artifactory/artifactory_api.py
devops_mcps/utils/artifactory/artifactory_auth.py
devops_mcps/utils/azure/__init__.py
devops_mcps/utils/azure/azure_app_service.py
devops_mcps/utils/azure/azure_auth.py
devops_mcps/utils/azure/azure_compute.py
devops_mcps/utils/azure/azure_containers.py
devops_mcps/utils/azure/azure_subscriptions.py
devops_mcps/utils/github/__init__.py
devops_mcps/utils/github/github_api.py
devops_mcps/utils/github/github_client.py
devops_mcps/utils/github/github_commit_api.py
devops_mcps/utils/github/github_converters.py
devops_mcps/utils/github/github_issue_api.py
devops_mcps/utils/github/github_repository_api.py
devops_mcps/utils/github/github_search_api.py
devops_mcps/utils/github/github_user_api.py
devops_mcps/utils/jenkins/__init__.py
devops_mcps/utils/jenkins/jenkins_api.py
devops_mcps/utils/jenkins/jenkins_build_api.py
devops_mcps/utils/jenkins/jenkins_builds.py
devops_mcps/utils/jenkins/jenkins_client.py
devops_mcps/utils/jenkins/jenkins_converters.py
devops_mcps/utils/jenkins/jenkins_helpers.py
devops_mcps/utils/jenkins/jenkins_job_api.py
devops_mcps/utils/jenkins/jenkins_logs.py
devops_mcps/utils/jenkins/jenkins_parameters.py
devops_mcps/utils/jenkins/jenkins_queue_api.py
devops_mcps/utils/jenkins/jenkins_view_api.py
devops_mcps-0.9.5.dist-info/licenses/LICENSE
devops_mcps-0.9.5.dist-info/METADATA
devops_mcps-0.9.5.dist-info/WHEEL
devops_mcps-0.9.5.dist-info/entry_points.txt
devops_mcps-0.9.5.dist-info/top_level.txt
devops_mcps-0.9.5.dist-info/RECORD
