Metadata-Version: 2.4
Name: devops-mcps
Version: 0.9.5
Summary: A FastMCP-based, Readonly MCP server for DevOps
Author-email: Jien Huang <huangjien@gmail.com>
Project-URL: Homepage, https://www.huangjien.com
Project-URL: Repository, https://github.com/huangjien/devops-mcps
Keywords: devops,mcp,python,cli,jenkins,azure,github
Classifier: Development Status :: 3 - Alpha
Classifier: Intended Audience :: Developers
Classifier: Intended Audience :: System Administrators
Classifier: Programming Language :: Python :: 3.12
Requires-Python: >=3.12
License-File: LICENSE
Requires-Dist: fastmcp>=2.11.0
Requires-Dist: pydantic
Requires-Dist: python-dotenv
Requires-Dist: toml
Requires-Dist: dotenv>=0.9.9
Requires-Dist: pygithub>=2.6.1
Requires-Dist: jenkinsapi==0.3.14
Requires-Dist: fastapi>=0.115.12
Requires-Dist: azure-identity>=1.15.0
Requires-Dist: azure-mgmt-compute>=30.6.0
Requires-Dist: azure-mgmt-containerservice>=28.1.0
Requires-Dist: azure-mgmt-subscription>=3.1.1
Requires-Dist: azure-mgmt-web>=7.0.0
Provides-Extra: dev
Requires-Dist: pyright>=1.1.389; extra == "dev"
Requires-Dist: ruff>=0.7.4; extra == "dev"
Requires-Dist: pytest>=8.3.5; extra == "dev"
Requires-Dist: pytest-cov>=6.1.1; extra == "dev"
Requires-Dist: pytest-mock>=3.14.0; extra == "dev"
Requires-Dist: pytest-asyncio; extra == "dev"
Dynamic: license-file
